pyhyrec/.DS_Store
pyhyrec/__init__.py
pyhyrec/__main__.py
pyhyrec/params.py
pyhyrec/wrapperhyrec.c
pyhyrec/wrapperhyrec.cpython-310-darwin.so
pyhyrec/wrapperhyrec.pyx
pyhyrec/data/Alpha_inf.dat
pyhyrec/data/R_inf.dat
pyhyrec/data/__init__.py
pyhyrec/data/fit_swift.dat
pyhyrec/data/two_photon_tables.dat
pyhyrec/data/two_photon_tables_hires.dat
pyhyrec/src/Makefile
pyhyrec/src/energy_injection.c
pyhyrec/src/energy_injection.h
pyhyrec/src/helium.c
pyhyrec/src/helium.h
pyhyrec/src/history.c
pyhyrec/src/history.h
pyhyrec/src/hydrogen.c
pyhyrec/src/hydrogen.h
pyhyrec/src/hyrec
pyhyrec/src/hyrec.c
pyhyrec/src/hyrectools.c
pyhyrec/src/hyrectools.h
pyhyrec/src/input.dat
pyhyrec/src/libhyrec.so
pyhyrec-1.0.0.dist-info/LICENSE
pyhyrec-1.0.0.dist-info/METADATA
pyhyrec-1.0.0.dist-info/WHEEL
pyhyrec-1.0.0.dist-info/top_level.txt
pyhyrec-1.0.0.dist-info/RECORD
