Metadata-Version: 2.1
Name: pyhyrec
Version: 1.0.0
Summary: A code for cosmological recombination history
Author: Nanoom Lee, Yacine Ali-Haimoud, Chris Hirata
Author-email: Gaétan Facchinetti <gaetanfacc@gmail.com>
License: GNU GENERAL PUBLIC LICENSE
Project-URL: Homepage, https://github.com/nanoomlee/HYREC-2
Project-URL: PythonVersion, https://github.com/gaetanfacchinetti/HYREC-2
Keywords: physics,cosmology,recombination
Classifier: License :: OSI Approved :: GNU General Public License v3 (GPLv3)
Classifier: Programming Language :: Python
Classifier: Programming Language :: Python :: 3
Classifier: Operating System :: Unix
Classifier: Operating System :: MacOS :: MacOS X
Requires-Python: >=3.6
License-File: LICENSE
Requires-Dist: cython
Requires-Dist: numpy
Provides-Extra: dev
